pybrewlib/__init__.py
pybrewlib/calculations.py
pybrewlib/cli.py
pybrewlib/lang_pack.py
pybrewlib-1.0.dist-info/LICENSE
pybrewlib-1.0.dist-info/METADATA
pybrewlib-1.0.dist-info/WHEEL
pybrewlib-1.0.dist-info/top_level.txt
pybrewlib-1.0.dist-info/RECORD
