Metadata-Version: 2.1
Name: pybrewlib
Version: 1.0
Summary: A set of calculations used in beer-making and wine-making hobbies
Author: hero24
Author-email: hero24 <hero24@interia.pl>
Project-URL: Homepage, https://github.com/hero24/pybrewlib/
Project-URL: Issues, https://github.com/hero24/pybrewlib/issues/
Classifier: Programming Language :: Python :: 3
Classifier: License :: OSI Approved :: GNU General Public License v2 (GPLv2)
Classifier: Operating System :: OS Independent
Requires-Python: >3.0
License-File: LICENSE
